{
  "numFound": 1,
  "documents": [
    {
      "id": "225954",
      "drucksachetyp": "Antrag",
      "dokumentart": "Drucksache",
      "autoren_anzahl": 10,
      "typ": "Dokument",
      "vorgangsbezug_anzahl": 1,
      "dokumentnummer": "19/7427",
      "wahlperiode": 19,
      "herausgeber": "BT",
      "pdf_hash": "29adbeee4907d5c77d66b53d361f7acf",
      "aktualisiert": "2022-07-26T19:57:15+02:00",
      "vorgangsbezug": [
        {
          "id": "243755",
          "titel": "Für eine neue Russlandpolitik - Kooperation statt Konfrontation",
          "vorgangstyp": "Antrag"
        }
      ],
      "urheber": [
        {
          "einbringer": false,
          "bezeichnung": "AfD",
          "titel": "Fraktion der AfD"
        }
      ],
      "fundstelle": {
        "pdf_url": "https://dserver.bundestag.de/btd/19/074/1907427.pdf",
        "id": "225954",
        "dokumentnummer": "19/7427",
        "datum": "2019-01-30",
        "dokumentart": "Drucksache",
        "drucksachetyp": "Antrag",
        "herausgeber": "BT",
        "urheber": [
          "Fraktion der AfD"
        ]
      },
      "autoren_anzeige": [
        {
          "id": "2173",
          "titel": "Dr. Anton Friesen, MdB, AfD",
          "autor_titel": "Dr. Anton Friesen"
        },
        {
          "id": "2111",
          "titel": "Dr. Robby Schlund, MdB, AfD",
          "autor_titel": "Dr. Robby Schlund"
        }
      ],
      "titel": "Für eine neue Russlandpolitik - Kooperation statt Konfrontation",
      "datum": "2019-01-30"
    }
  ],
  "cursor": "AoJw-Myaz-gCMURydWNrc2FjaGUtMjI1OTU0"
}